DiffPriv/__init__.py
DiffPriv/cli.py
DiffPriv/diff.py
DiffPriv/enc.py
DiffPriv-1.0.3.dist-info/LICENSE
DiffPriv-1.0.3.dist-info/METADATA
DiffPriv-1.0.3.dist-info/WHEEL
DiffPriv-1.0.3.dist-info/entry_points.txt
DiffPriv-1.0.3.dist-info/top_level.txt
DiffPriv-1.0.3.dist-info/RECORD
