Metadata-Version: 2.1
Name: DiffPriv
Version: 1.0.3
Summary: A Differential Privacy Package
Home-page: https://github.com/Quantalabs/DiffPriv
Author: Quantalabs
License: UNKNOWN
Project-URL: Documentation, https://quantalabs.github.io/DiffPriv/docs/
Project-URL: Source, https://github.com/Quantalabs/DiffPriv
Project-URL: Tracker, https://github.com/Quantalabs/DiffPriv/issues
Project-URL: Changelog, https://quantalabs.github.io/DiffPriv/CHANGELOG
Project-URL: Download, https://pypi.org/project/DiffPriv/#files
Project-URL: Code Coverage, https://app.codecov.io/gh/Quantalabs/DiffPriv
Project-URL: Forum, https://github.com/Quantalabs/DiffPriv/discussions
Project-URL: Conda Forge, https://anaconda.org/conda-forge/diffpriv
Platform: UNKNOWN
Classifier: Programming Language :: Python :: 3
Classifier: License :: OSI Approved :: GNU General Public License v3 (GPLv3)
Classifier: Operating System :: OS Independent
Requires-Python: >= 3.8.1
